[
  {
    "review_id":477990190890,
    "rating":2,
    "text":"처음 받은 제품이 한쪽이 배터리 충전 안되고 케이스 충전 상황이 안떠서 교환했다가 재고부족으로 환불처리되어서 겨우 새로 예약 구매해서 받았네요... 기존 기종 - 프로1, 줄이어폰 번갈아 사용 프로1 고장난지 꽤 됐는데(노이즈캔슬링 안됨 + 배터리 빨리 닳음, 첫 착용시 치지직 소리 등) 에어팟 가격이 부담되기도하고 그냥 부가적으로 줄이어폰이나 쓰자싶어 쭉 버티다가 겨울되면 정전기로 줄이어폰 불편할 것 같아 이참에 프로3으로 업글했습니다. 기본형이랑 프로랑 장단점이 너무 달라서 고민됐는데 그래도 비싼 값어치 하겠지싶어서 그냥 프로로 샀어요... 일단 처음에 끼워져있는 고무로 사용해봤을땐 프로1에 비해 제 귀엔 사알짝 헐렁한 느낌이 들어서 뛰면 빠질 것 같은 느낌이 들어 불안했습니다. 그리고 노이즈캔슬링모드 사용하니까 전 울렁거릴정도여서 적응 안되면 노캔기능 끄고 사용해야할 것 같아요ㅠㅠㅠ🥹... 잠깐 사용하다가 넣어뒀는데 본체에서 계속 띠리리링 소리가 나네요...하....고장으로 쳐줘서 교환가능할지는 모르겠지만 한달동안 두번이나 이런 제품 받으니까 너무 열받네요. + 서비스센터 다녀온 후기 추가합니다. 제품이 인식하는 소리라 계속적으로 원래 나는게 정상이라고 고장처리가 안된다네요. 사기 전으로 돌아간다면 전 안살래요. 사십만원 날림ㅋ 전 프로1이 맛이 가서 어쩔 수 없이 바꾼거지만 호불호가 갈릴 것 같아 프로3을 굳이 추천하고싶진 않아요..",
    "created_at":"2025-11-12T18:38:21Z"
  },
  {
    "review_id":867149197981,
    "rating":1,
    "text":"포장이 최악이예요. 테입하나 안붙이고 비닐에 덜렁...열었더니 비닐에서 빠져서 박스에 뒹굴고 있었구요. 뽁뽁이 비용이 그리 아깝나요? 에어가 다 터진 비닐이였어요. 박스도 간만에 보는 얇은 두께네요. 전자제품을 완충작용 하나없는 포장으로 보내다가 망가지면 어쩌려는 걸까요? 과대포장 싫어하는 사람이지만 에어가 다 터진 비닐 사용에 성의없이 테입으로 여미지도 않은 포장은 정말 문제가 있습니다. 너무 한거 아닌가요.",
    "created_at":"2025-12-29T20:06:52Z"
  }
]